[
  {
    "model": "D'Addario",
    "title": "Woodwinds VENN G2 Sentetik Bb Klarnet Kamışı No:2",
    "price": "1.592 TL",
    "rating": "N/A",
    "evaluation": "N/A",
    "category_url": "https://www.hepsiburada.com/nefesli-calgi-aksesuarlari-c-411156?sayfa=15",
    "product_url": "https://www.hepsiburada.com/d-addario-venn-g2-sentetik-bb-klarnet-kamisi-no-2-pm-HBC00002JC8ZH",
    "category": "Nefesli Çalgı Aksesuarları",
    "supercategory": "Müzik & Müzik Aletleri"
  },
  {
    "model": "Rico Royal",
    "title": "Select Jazz Alto Saksafon Beki No.7",
    "price": "7.974 TL",
    "rating": "N/A",
    "evaluation": "N/A",
    "category_url": "https://www.hepsiburada.com/nefesli-calgi-aksesuarlari-c-411156?sayfa=15",
    "product_url": "https://www.hepsiburada.com/rico-royal-select-jazz-alto-saksafon-beki-no-7-pm-HB00000AC64L",
    "category": "Nefesli Çalgı Aksesuarları",
    "supercategory": "Müzik & Müzik Aletleri"
  },
  {
    "model": "Rovner",
    "title": "Klarnet. Deri Bilezik Seti Lıght Model",
    "price": "1.587,50 TL",
    "rating": "N/A",
    "evaluation": "N/A",
    "category_url": "https://www.hepsiburada.com/nefesli-calgi-aksesuarlari-c-411156?sayfa=15",
    "product_url": "https://www.hepsiburada.com/rovner-klarnet-deri-bilezik-seti-light-model-pm-HB000013FNJJ",
    "category": "Nefesli Çalgı Aksesuarları",
    "supercategory": "Müzik & Müzik Aletleri"
  },
  {
    "model": "Segah Müzik",
    "title": "3/4 Keman Çenelik - Sağ Çenelik",
    "price": "270 TL",
    "rating": "N/A",
    "evaluation": "N/A",
    "category_url": "https://www.hepsiburada.com/nefesli-calgi-aksesuarlari-c-411156?sayfa=15",
    "product_url": "https://www.hepsiburada.com/3-4-keman-cenelik-sag-cenelik-pm-HBC000032Y66H",
    "category": "Nefesli Çalgı Aksesuarları",
    "supercategory": "Müzik & Müzik Aletleri"
  },
  {
    "model": "Rico Royal",
    "title": "RIB1030 Soprano Sax Kamışı No:3",
    "price": "898,50 TL",
    "rating": "N/A",
    "evaluation": "N/A",
    "category_url": "https://www.hepsiburada.com/nefesli-calgi-aksesuarlari-c-411156?sayfa=15",
    "product_url": "https://www.hepsiburada.com/rico-royal-rib1030-soprano-sax-kamisi-no-3-pm-HB000004GQX2",
    "category": "Nefesli Çalgı Aksesuarları",
    "supercategory": "Müzik & Müzik Aletleri"
  },
  {
    "model": "Vandoren",
    "title": "Bek Dişlik Siyah Vmcx6 0,80Mm",
    "price": "517,50 TL",
    "rating": "5",
    "evaluation": "(4)",
    "category_url": "https://www.hepsiburada.com/nefesli-calgi-aksesuarlari-c-411156?sayfa=15",
    "product_url": "https://www.hepsiburada.com/imecemuzik-vandoren-bek-dislik-siyah-vmcx6-0-80mm-pm-musicalmzk14256906",
    "category": "Nefesli Çalgı Aksesuarları",
    "supercategory": "Müzik & Müzik Aletleri"
  },
  {
    "model": "İmece",
    "title": "Maxtone PF18-B Maxtone Pan Flüt 8 Nota",
    "price": "2.729,77 TL",
    "rating": "N/A",
    "evaluation": "N/A",
    "category_url": "https://www.hepsiburada.com/nefesli-calgi-aksesuarlari-c-411156?sayfa=15",
    "product_url": "https://www.hepsiburada.com/imece-maxtone-pf18-b-maxtone-pan-flut-8-nota-pm-HBC000025DQLP",
    "category": "Nefesli Çalgı Aksesuarları",
    "supercategory": "Müzik & Müzik Aletleri"
  },
  {
    "model": "Barre",
    "title": "Klarnet Kamış No.1 Bb",
    "price": "948,49 TL",
    "rating": "N/A",
    "evaluation": "N/A",
    "category_url": "https://www.hepsiburada.com/nefesli-calgi-aksesuarlari-c-411156?sayfa=15",
    "product_url": "https://www.hepsiburada.com/barre-klarnet-kamis-no-1-bb-pm-HBC00000QJREO",
    "category": "Nefesli Çalgı Aksesuarları",
    "supercategory": "Müzik & Müzik Aletleri"
  },
  {
    "model": "LongMoon",
    "title": "Longmoon GSAK2T Alto Saksafon Kamışı No:2 Rıyın (1 Adet)",
    "price": "133,85 TL",
    "rating": "N/A",
    "evaluation": "N/A",
    "category_url": "https://www.hepsiburada.com/nefesli-calgi-aksesuarlari-c-411156?sayfa=15",
    "product_url": "https://www.hepsiburada.com/longmoon-gsak2t-alto-saksafon-kamisi-no-2-riyin-1-adet-pm-HBC00002IE7GD",
    "category": "Nefesli Çalgı Aksesuarları",
    "supercategory": "Müzik & Müzik Aletleri"
  },
  {
    "model": "Cremonia",
    "title": "Kp-2 Plastik Kazoo Yeşil",
    "price": "181,63 TL",
    "rating": "5",
    "evaluation": "(1)",
    "category_url": "https://www.hepsiburada.com/nefesli-calgi-aksesuarlari-c-411156?sayfa=15",
    "product_url": "https://www.hepsiburada.com/cremonia-kp-2-plastik-kazoo-yesil-pm-HBC00000WZYCF",
    "category": "Nefesli Çalgı Aksesuarları",
    "supercategory": "Müzik & Müzik Aletleri"
  },
  {
    "model": "İmece",
    "title": "Imece Sba-19 Derlin Başpare 19 mm",
    "price": "222,42 TL",
    "rating": "5",
    "evaluation": "(2)",
    "category_url": "https://www.hepsiburada.com/nefesli-calgi-aksesuarlari-c-411156?sayfa=15",
    "product_url": "https://www.hepsiburada.com/imece-sba-19-derlin-baspare-19-mm-pm-HBC000023LA4Z",
    "category": "Nefesli Çalgı Aksesuarları",
    "supercategory": "Müzik & Müzik Aletleri"
  },
  {
    "model": "Fox",
    "title": "Mut-Tr3 Trompet Susturucu",
    "price": "1.395,21 TL",
    "rating": "N/A",
    "evaluation": "N/A",
    "category_url": "https://www.hepsiburada.com/nefesli-calgi-aksesuarlari-c-411156?sayfa=15",
    "product_url": "https://www.hepsiburada.com/fox-mut-tr3-trompet-susturucu-pm-HBC000025H4EK",
    "category": "Nefesli Çalgı Aksesuarları",
    "supercategory": "Müzik & Müzik Aletleri"
  },
  {
    "model": "Barre",
    "title": "Klarnet Kamış No:1.5 10'Lu Paket",
    "price": "879,84 TL",
    "rating": "5",
    "evaluation": "(1)",
    "category_url": "https://www.hepsiburada.com/nefesli-calgi-aksesuarlari-c-411156?sayfa=15",
    "product_url": "https://www.hepsiburada.com/barre-klarnet-kamis-barre-no-1-5-bb-pm-HBC00001DNVLC",
    "category": "Nefesli Çalgı Aksesuarları",
    "supercategory": "Müzik & Müzik Aletleri"
  },
  {
    "model": "Rico Royal",
    "title": "RCC10MD Lavoz Klarnet Kamışı Medium",
    "price": "1.172,79 TL",
    "rating": "N/A",
    "evaluation": "N/A",
    "category_url": "https://www.hepsiburada.com/nefesli-calgi-aksesuarlari-c-411156?sayfa=15",
    "product_url": "https://www.hepsiburada.com/rico-royal-rcc10md-lavoz-klarnet-kamisi-medium-pm-HBC000025H4E0",
    "category": "Nefesli Çalgı Aksesuarları",
    "supercategory": "Müzik & Müzik Aletleri"
  },
  {
    "model": "J.Michael",
    "title": "J.michael R-Cl Klarnet Kamışı 3 No",
    "price": "404,41 TL",
    "rating": "N/A",
    "evaluation": "N/A",
    "category_url": "https://www.hepsiburada.com/nefesli-calgi-aksesuarlari-c-411156?sayfa=15",
    "product_url": "https://www.hepsiburada.com/j-michael-r-cl-klarnet-kamisi-3-no-pm-HBC000025H4EU",
    "category": "Nefesli Çalgı Aksesuarları",
    "supercategory": "Müzik & Müzik Aletleri"
  },
  {
    "model": "Bade",
    "title": "Mehter Zurna Kamışı Borulu (Pirinç)",
    "price": "359,99 TL",
    "rating": "N/A",
    "evaluation": "N/A",
    "category_url": "https://www.hepsiburada.com/nefesli-calgi-aksesuarlari-c-411156?sayfa=15",
    "product_url": "https://www.hepsiburada.com/bade-mehter-zurna-kamisi-borulu-pirinc-pm-HB00001309IL",
    "category": "Nefesli Çalgı Aksesuarları",
    "supercategory": "Müzik & Müzik Aletleri"
  },
  {
    "model": "N/A",
    "title": "Daddario Woodwinds MCR-X15E Sib Klarnet Beki (Medium Open)",
    "price": "6.263 TL",
    "rating": "N/A",
    "evaluation": "N/A",
    "category_url": "https://www.hepsiburada.com/nefesli-calgi-aksesuarlari-c-411156?sayfa=15",
    "product_url": "https://www.hepsiburada.com/daddario-woodwinds-mcr-x15e-sib-klarnet-beki-medium-open-pm-HB00000N3PXO",
    "category": "Nefesli Çalgı Aksesuarları",
    "supercategory": "Müzik & Müzik Aletleri"
  },
  {
    "model": "Vandoren",
    "title": "V12 Bb Clarinet Reeds No:3.5 Bb Klarnet Kamışı",
    "price": "2.314,07 TL",
    "rating": "N/A",
    "evaluation": "N/A",
    "category_url": "https://www.hepsiburada.com/nefesli-calgi-aksesuarlari-c-411156?sayfa=15",
    "product_url": "https://www.hepsiburada.com/vandoren-v12-bb-clarinet-reeds-no-3-5-bb-klarnet-kamisi-pm-HBC00004CLJME",
    "category": "Nefesli Çalgı Aksesuarları",
    "supercategory": "Müzik & Müzik Aletleri"
  },
  {
    "model": "Rico Royal",
    "title": "Plasticover Bb Clarinet 2 Bb Klarnet Kamışı",
    "price": "1.173,15 TL",
    "rating": "N/A",
    "evaluation": "N/A",
    "category_url": "https://www.hepsiburada.com/nefesli-calgi-aksesuarlari-c-411156?sayfa=15",
    "product_url": "https://www.hepsiburada.com/rico-royal-plasticover-bb-clarinet-2-bb-klarnet-kamisi-pm-HBC00004NW0D2",
    "category": "Nefesli Çalgı Aksesuarları",
    "supercategory": "Müzik & Müzik Aletleri"
  },
  {
    "model": "Rico Royal",
    "title": "Rcr Reserve Bb Clarinet 3 Bb Klarnet Kamışı - 5 Adet",
    "price": "1.151,93 TL",
    "rating": "N/A",
    "evaluation": "N/A",
    "category_url": "https://www.hepsiburada.com/nefesli-calgi-aksesuarlari-c-411156?sayfa=15",
    "product_url": "https://www.hepsiburada.com/rico-royal-rcr-reserve-bb-clarinet-3-bb-klarnet-kamisi-5-adet-pm-HBC00003YAXKZ",
    "category": "Nefesli Çalgı Aksesuarları",
    "supercategory": "Müzik & Müzik Aletleri"
  },
  {
    "model": "Franck Bichon",
    "title": "Klarnet Aksesuar Bilezik Lastik Destekli Bg Franck Bichon L6",
    "price": "1.631,20 TL",
    "rating": "N/A",
    "evaluation": "N/A",
    "category_url": "https://www.hepsiburada.com/nefesli-calgi-aksesuarlari-c-411156?sayfa=15",
    "product_url": "https://www.hepsiburada.com/franck-bichon-klarnet-aksesuar-bilezik-lastik-destekli-bg-franck-bichon-l6-pm-music441597",
    "category": "Nefesli Çalgı Aksesuarları",
    "supercategory": "Müzik & Müzik Aletleri"
  },
  {
    "model": "Ton Kooiman",
    "title": "Ayarlı Klarnet Parmak Dayama Aparatı Small",
    "price": "1.894,50 TL",
    "rating": "5",
    "evaluation": "(1)",
    "category_url": "https://www.hepsiburada.com/nefesli-calgi-aksesuarlari-c-411156?sayfa=15",
    "product_url": "https://www.hepsiburada.com/ton-kooiman-ayarli-klarnet-parmak-dayama-aparati-small-pm-HB000013FZFM",
    "category": "Nefesli Çalgı Aksesuarları",
    "supercategory": "Müzik & Müzik Aletleri"
  },
  {
    "model": "Ardor",
    "title": "Klarnet Bilezik Gümüş Kaplama",
    "price": "784,34 TL",
    "rating": "N/A",
    "evaluation": "N/A",
    "category_url": "https://www.hepsiburada.com/nefesli-calgi-aksesuarlari-c-411156?sayfa=15",
    "product_url": "https://www.hepsiburada.com/ardor-klarnet-bilezik-gumus-kaplama-pm-HBC00000N47L5",
    "category": "Nefesli Çalgı Aksesuarları",
    "supercategory": "Müzik & Müzik Aletleri"
  },
  {
    "model": "Segah Müzik",
    "title": "Zeynel Abidin Cümbüş Kılıfı Standart",
    "price": "720 TL",
    "rating": "N/A",
    "evaluation": "N/A",
    "category_url": "https://www.hepsiburada.com/nefesli-calgi-aksesuarlari-c-411156?sayfa=15",
    "product_url": "https://www.hepsiburada.com/zeynel-abidin-cumbus-kilifi-standart-pm-HBC00004G0O53",
    "category": "Nefesli Çalgı Aksesuarları",
    "supercategory": "Müzik & Müzik Aletleri"
  },
  {
    "model": "Crown Well",
    "title": "Gramafon Parça'sı Diyafram Ayağı",
    "price": "1.655 TL",
    "rating": "N/A",
    "evaluation": "N/A",
    "category_url": "https://www.hepsiburada.com/nefesli-calgi-aksesuarlari-c-411156?sayfa=15",
    "product_url": "https://www.hepsiburada.com/crown-well-gramafon-parca-si-diyafram-ayagi-pm-HBC0000034SXF",
    "category": "Nefesli Çalgı Aksesuarları",
    "supercategory": "Müzik & Müzik Aletleri"
  },
  {
    "model": "Jazz Müzik",
    "title": "Plastik Ney Başpare",
    "price": "149,90 TL",
    "rating": "N/A",
    "evaluation": "N/A",
    "category_url": "https://www.hepsiburada.com/nefesli-calgi-aksesuarlari-c-411156?sayfa=15",
    "product_url": "https://www.hepsiburada.com/jazz-muzik-plastik-ney-baspare-pm-HBC00003H3KYO",
    "category": "Nefesli Çalgı Aksesuarları",
    "supercategory": "Müzik & Müzik Aletleri"
  },
  {
    "model": "Black Raven",
    "title": "Ayarlı Klarnet Bareli BR-020",
    "price": "2.057,50 TL",
    "rating": "N/A",
    "evaluation": "N/A",
    "category_url": "https://www.hepsiburada.com/nefesli-calgi-aksesuarlari-c-411156?sayfa=15",
    "product_url": "https://www.hepsiburada.com/black-raven-ayarli-klarnet-bareli-br-020-pm-HBC000001U6PL",
    "category": "Nefesli Çalgı Aksesuarları",
    "supercategory": "Müzik & Müzik Aletleri"
  },
  {
    "model": "Yamaha",
    "title": "Pudralı Kağıt Yac 1112-P",
    "price": "1.370,13 TL",
    "rating": "N/A",
    "evaluation": "N/A",
    "category_url": "https://www.hepsiburada.com/nefesli-calgi-aksesuarlari-c-411156?sayfa=15",
    "product_url": "https://www.hepsiburada.com/yamaha-pudrali-kagit-yac-1112-p-pm-HBC000091U3AX",
    "category": "Nefesli Çalgı Aksesuarları",
    "supercategory": "Müzik & Müzik Aletleri"
  },
  {
    "model": "Chiarugi",
    "title": "Abanoz Çift Taraflı Obua Için Dil AC.172D",
    "price": "316,18 TL",
    "rating": "N/A",
    "evaluation": "N/A",
    "category_url": "https://www.hepsiburada.com/nefesli-calgi-aksesuarlari-c-411156?sayfa=15",
    "product_url": "https://www.hepsiburada.com/chiarugi-abanoz-cift-tarafli-obua-icin-dil-ac-172d-pm-HBC000091MZID",
    "category": "Nefesli Çalgı Aksesuarları",
    "supercategory": "Müzik & Müzik Aletleri"
  },
  {
    "model": "Vandoren",
    "title": "SR263R Java Red Cut Alto Sax Kamışı (10'lu) No. 3",
    "price": "1.939 TL",
    "rating": "N/A",
    "evaluation": "N/A",
    "category_url": "https://www.hepsiburada.com/nefesli-calgi-aksesuarlari-c-411156?sayfa=15",
    "product_url": "https://www.hepsiburada.com/vandoren-sr263r-java-red-cut-alto-sax-kamisi-10-lu-no-3-pm-HBC000056KXG0",
    "category": "Nefesli Çalgı Aksesuarları",
    "supercategory": "Müzik & Müzik Aletleri"
  },
  {
    "model": "Chiarugi",
    "title": "Obua Için Ip AC.174A",
    "price": "685,06 TL",
    "rating": "N/A",
    "evaluation": "N/A",
    "category_url": "https://www.hepsiburada.com/nefesli-calgi-aksesuarlari-c-411156?sayfa=15",
    "product_url": "https://www.hepsiburada.com/chiarugi-obua-icin-ip-ac-174a-pm-HBC000091MZLU",
    "category": "Nefesli Çalgı Aksesuarları",
    "supercategory": "Müzik & Müzik Aletleri"
  },
  {
    "model": "Coda Bow",
    "title": "Codabow Marquise Aero Yuvarlak Topuk Karbon Çello Arşesi Aeroc",
    "price": "74.775,62 TL",
    "rating": "N/A",
    "evaluation": "N/A",
    "category_url": "https://www.hepsiburada.com/nefesli-calgi-aksesuarlari-c-411156?sayfa=15",
    "product_url": "https://www.hepsiburada.com/codabow-marquise-aero-yuvarlak-topuk-karbon-cello-arsesi-aeroc-pm-HBC000091MZVH",
    "category": "Nefesli Çalgı Aksesuarları",
    "supercategory": "Müzik & Müzik Aletleri"
  },
  {
    "model": "SAZ",
    "title": "761-B Mey Kamışı",
    "price": "450 TL",
    "rating": "N/A",
    "evaluation": "N/A",
    "category_url": "https://www.hepsiburada.com/nefesli-calgi-aksesuarlari-c-411156?sayfa=15",
    "product_url": "https://www.hepsiburada.com/saz-761-b-mey-kamisi-pm-musicsaz163",
    "category": "Nefesli Çalgı Aksesuarları",
    "supercategory": "Müzik & Müzik Aletleri"
  },
  {
    "model": "Yamaha",
    "title": "CL 5C Sib Klarnet Beki",
    "price": "3.057,50 TL",
    "rating": "N/A",
    "evaluation": "N/A",
    "category_url": "https://www.hepsiburada.com/nefesli-calgi-aksesuarlari-c-411156?sayfa=15",
    "product_url": "https://www.hepsiburada.com/yamaha-cl-5c-sib-klarnet-beki-pm-HB00000ELZ6K",
    "category": "Nefesli Çalgı Aksesuarları",
    "supercategory": "Müzik & Müzik Aletleri"
  },
  {
    "model": "Rigotti",
    "title": "Klarnet Aks Guderi Takım Deri Kahve (Rpc17Lb)",
    "price": "1.179,60 TL",
    "rating": "2",
    "evaluation": "(1)",
    "category_url": "https://www.hepsiburada.com/nefesli-calgi-aksesuarlari-c-411156?sayfa=15",
    "product_url": "https://www.hepsiburada.com/rigotti-klarnet-aks-guderi-takim-deri-kahve-rpc17lb-pm-HB00000FN58S",
    "category": "Nefesli Çalgı Aksesuarları",
    "supercategory": "Müzik & Müzik Aletleri"
  },
  {
    "model": "Cremonia",
    "title": "CR32PK",
    "price": "831,04 TL",
    "rating": "N/A",
    "evaluation": "N/A",
    "category_url": "https://www.hepsiburada.com/nefesli-calgi-aksesuarlari-c-411156?sayfa=15",
    "product_url": "https://www.hepsiburada.com/cremonia-cr32pk-pm-HBC000030X39X",
    "category": "Nefesli Çalgı Aksesuarları",
    "supercategory": "Müzik & Müzik Aletleri"
  }
]