[
  {
    "model": "Brilant",
    "title": "katlanır oyuncak kutusu çamaşır sepeti",
    "price": "292,01 TL",
    "rating": "N/A",
    "evaluation": "N/A",
    "category_url": "https://www.hepsiburada.com/oyuncak-kutulari-c-23020686?sayfa=35",
    "product_url": "https://www.hepsiburada.com/brilant-oyuncak-pm-HBC00006TOZ71",
    "category": "Oyuncak Kutuları",
    "supercategory": "Bebek Odası ve Tekstili"
  },
  {
    "model": "Blue Global",
    "title": "Çocuk Oyuncak Saklama Çantası - Beyaz (Yurt Dışından)",
    "price": "1.150,80 TL",
    "rating": "2",
    "evaluation": "(1)",
    "category_url": "https://www.hepsiburada.com/oyuncak-kutulari-c-23020686?sayfa=35",
    "product_url": "https://www.hepsiburada.com/blue-global-cocuk-oyuncak-saklama-cantasi-beyaz-yurt-disindan-pm-HBC0000315VCL",
    "category": "Oyuncak Kutuları",
    "supercategory": "Bebek Odası ve Tekstili"
  },
  {
    "model": "Mekta Home",
    "title": "Bebek ve Çocuk Odası Gökyüzü Desenli Oyuncak Sepeti",
    "price": "418,95 TL",
    "rating": "N/A",
    "evaluation": "N/A",
    "category_url": "https://www.hepsiburada.com/oyuncak-kutulari-c-23020686?sayfa=35",
    "product_url": "https://www.hepsiburada.com/mekta-home-bebek-ve-cocuk-odasi-gokyuzu-desenli-oyuncak-sepeti-pm-HBC00005K7MAD",
    "category": "Oyuncak Kutuları",
    "supercategory": "Bebek Odası ve Tekstili"
  },
  {
    "model": "Mekta Home",
    "title": "Bebek ve Çocuk Odası Ay ve Ayı Desenli Oyuncak Sepeti",
    "price": "418,95 TL",
    "rating": "N/A",
    "evaluation": "N/A",
    "category_url": "https://www.hepsiburada.com/oyuncak-kutulari-c-23020686?sayfa=35",
    "product_url": "https://www.hepsiburada.com/mekta-home-bebek-ve-cocuk-odasi-ay-ve-ayi-desenli-oyuncak-sepeti-pm-HBC00005K7NAS",
    "category": "Oyuncak Kutuları",
    "supercategory": "Bebek Odası ve Tekstili"
  },
  {
    "model": "instababyrooms",
    "title": "Dijital Baskılı Çok Amaçlı Sepet Model 40048",
    "price": "399 TL",
    "rating": "5",
    "evaluation": "(1)",
    "category_url": "https://www.hepsiburada.com/oyuncak-kutulari-c-23020686?sayfa=35",
    "product_url": "https://www.hepsiburada.com/instababyrooms-dijital-baskili-cok-amacli-sepet-model-40048-pm-HBC000044ZZS6",
    "category": "Oyuncak Kutuları",
    "supercategory": "Bebek Odası ve Tekstili"
  },
  {
    "model": "Mekta Home",
    "title": "Bebek ve Çocuk Odası Gezegen ve Space x Desenli Oyuncak Sepeti",
    "price": "418,95 TL",
    "rating": "N/A",
    "evaluation": "N/A",
    "category_url": "https://www.hepsiburada.com/oyuncak-kutulari-c-23020686?sayfa=35",
    "product_url": "https://www.hepsiburada.com/mekta-home-bebek-ve-cocuk-odasi-gezegen-ve-space-x-desenli-oyuncak-sepeti-pm-HBC00005K7O4S",
    "category": "Oyuncak Kutuları",
    "supercategory": "Bebek Odası ve Tekstili"
  },
  {
    "model": "Mekta Home",
    "title": "Bebek ve Çocuk Odası Spider-Man Desenli Oyuncak Sepeti",
    "price": "418,95 TL",
    "rating": "N/A",
    "evaluation": "N/A",
    "category_url": "https://www.hepsiburada.com/oyuncak-kutulari-c-23020686?sayfa=35",
    "product_url": "https://www.hepsiburada.com/mekta-home-bebek-ve-cocuk-odasi-spider-man-desenli-oyuncak-sepeti-pm-HBC00005K7ITW",
    "category": "Oyuncak Kutuları",
    "supercategory": "Bebek Odası ve Tekstili"
  },
  {
    "model": "Mekta Home",
    "title": "Bebek ve Çocuk Odası Aslan Desenli Oyuncak Sepeti",
    "price": "418,95 TL",
    "rating": "N/A",
    "evaluation": "N/A",
    "category_url": "https://www.hepsiburada.com/oyuncak-kutulari-c-23020686?sayfa=35",
    "product_url": "https://www.hepsiburada.com/mekta-home-bebek-ve-cocuk-odasi-aslan-desenli-oyuncak-sepeti-pm-HBC00005K7NVB",
    "category": "Oyuncak Kutuları",
    "supercategory": "Bebek Odası ve Tekstili"
  },
  {
    "model": "Mekta Home",
    "title": "Bebek ve Çocuk Odası Çiçekli Kuğu Desenli Oyuncak Sepeti",
    "price": "418,95 TL",
    "rating": "N/A",
    "evaluation": "N/A",
    "category_url": "https://www.hepsiburada.com/oyuncak-kutulari-c-23020686?sayfa=35",
    "product_url": "https://www.hepsiburada.com/mekta-home-bebek-ve-cocuk-odasi-cicekli-kugu-desenli-oyuncak-sepeti-pm-HBC00005K7IA0",
    "category": "Oyuncak Kutuları",
    "supercategory": "Bebek Odası ve Tekstili"
  },
  {
    "model": "Mekta Home",
    "title": "Bebek ve Çocuk Odası Kral Taç Desenli Oyuncak Sepeti",
    "price": "418,95 TL",
    "rating": "N/A",
    "evaluation": "N/A",
    "category_url": "https://www.hepsiburada.com/oyuncak-kutulari-c-23020686?sayfa=35",
    "product_url": "https://www.hepsiburada.com/mekta-home-bebek-ve-cocuk-odasi-kral-tac-desenli-oyuncak-sepeti-pm-HBC00005K7NR3",
    "category": "Oyuncak Kutuları",
    "supercategory": "Bebek Odası ve Tekstili"
  },
  {
    "model": "Mekta Home",
    "title": "Bebek ve Çocuk Odası Pembe Bisiklet Balon ve Fil Desenli Oyuncak Sepeti",
    "price": "418,95 TL",
    "rating": "N/A",
    "evaluation": "N/A",
    "category_url": "https://www.hepsiburada.com/oyuncak-kutulari-c-23020686?sayfa=35",
    "product_url": "https://www.hepsiburada.com/mekta-home-bebek-ve-cocuk-odasi-pembe-bisiklet-balon-ve-fil-desenli-oyuncak-sepeti-pm-HBC00005K7ML8",
    "category": "Oyuncak Kutuları",
    "supercategory": "Bebek Odası ve Tekstili"
  },
  {
    "model": "Mekta Home",
    "title": "Bebek ve Çocuk Odası Yıldız ve Ay Desenli Çerçeveli Oyuncak Sepeti",
    "price": "418,95 TL",
    "rating": "N/A",
    "evaluation": "N/A",
    "category_url": "https://www.hepsiburada.com/oyuncak-kutulari-c-23020686?sayfa=35",
    "product_url": "https://www.hepsiburada.com/mekta-home-bebek-ve-cocuk-odasi-yildiz-ve-ay-desenli-cerceveli-oyuncak-sepeti-pm-HBC00005K7MAZ",
    "category": "Oyuncak Kutuları",
    "supercategory": "Bebek Odası ve Tekstili"
  },
  {
    "model": "Mekta Home",
    "title": "Bebek ve Çocuk Odası Balerin Kız ve Kedi Desenli Motifli Oyuncak Sepeti",
    "price": "418,95 TL",
    "rating": "N/A",
    "evaluation": "N/A",
    "category_url": "https://www.hepsiburada.com/oyuncak-kutulari-c-23020686?sayfa=35",
    "product_url": "https://www.hepsiburada.com/mekta-home-bebek-ve-cocuk-odasi-balerin-kiz-ve-kedi-desenli-motifli-oyuncak-sepeti-pm-HBC00005K7NVZ",
    "category": "Oyuncak Kutuları",
    "supercategory": "Bebek Odası ve Tekstili"
  },
  {
    "model": "Mekta Home",
    "title": "Bebek ve Çocuk Odası Şapkalı Yıldız ve Ay Desenli Oyuncak Sepeti",
    "price": "418,95 TL",
    "rating": "N/A",
    "evaluation": "N/A",
    "category_url": "https://www.hepsiburada.com/oyuncak-kutulari-c-23020686?sayfa=35",
    "product_url": "https://www.hepsiburada.com/mekta-home-bebek-ve-cocuk-odasi-sapkali-yildiz-ve-ay-desenli-oyuncak-sepeti-pm-HBC00005K7N1P",
    "category": "Oyuncak Kutuları",
    "supercategory": "Bebek Odası ve Tekstili"
  },
  {
    "model": "Mekta Home",
    "title": "Bebek ve Çocuk Odası Eğitici Şehir Desenli Yollu Oyuncak Sepeti",
    "price": "418,95 TL",
    "rating": "N/A",
    "evaluation": "N/A",
    "category_url": "https://www.hepsiburada.com/oyuncak-kutulari-c-23020686?sayfa=35",
    "product_url": "https://www.hepsiburada.com/mekta-home-bebek-ve-cocuk-odasi-egitici-sehir-desenli-yollu-oyuncak-sepeti-pm-HBC00005K7NKB",
    "category": "Oyuncak Kutuları",
    "supercategory": "Bebek Odası ve Tekstili"
  },
  {
    "model": "Woll Tasarım",
    "title": "2'li Sevimli Beyaz Panda Figürlü Oyuncak Çamaşır Sepeti 40X50 cm 30X30 cm",
    "price": "749 TL",
    "rating": "N/A",
    "evaluation": "N/A",
    "category_url": "https://www.hepsiburada.com/oyuncak-kutulari-c-23020686?sayfa=35",
    "product_url": "https://www.hepsiburada.com/woll-tasarim-2-li-sevimli-beyaz-panda-figurlu-oyuncak-camasir-sepeti-40x50-cm-30x30-cm-pm-HBC00000GEV05",
    "category": "Oyuncak Kutuları",
    "supercategory": "Bebek Odası ve Tekstili"
  },
  {
    "model": "Patiska Tasarım",
    "title": "Jüt Sepet El Örmesi Jüt Düzenleyici Sepet, Gri Kulplu Jüt Sepet",
    "price": "367,08 TL",
    "rating": "N/A",
    "evaluation": "N/A",
    "category_url": "https://www.hepsiburada.com/oyuncak-kutulari-c-23020686?sayfa=35",
    "product_url": "https://www.hepsiburada.com/patiska-tasarim-jut-sepet-el-ormesi-jut-duzenleyici-sepet-gri-kulplu-jut-sepet-pm-HBC0000661WVM",
    "category": "Oyuncak Kutuları",
    "supercategory": "Bebek Odası ve Tekstili"
  },
  {
    "model": "Popcorn Kids",
    "title": "Explorer Oyuncak Kutusu Sandık - Kahverengi",
    "price": "3.950 TL",
    "rating": "1",
    "evaluation": "(1)",
    "category_url": "https://www.hepsiburada.com/oyuncak-kutulari-c-23020686?sayfa=35",
    "product_url": "https://www.hepsiburada.com/popcorn-kids-explorer-oyuncak-kutusu-sandik-kahverengi-pm-HB000014ZARY",
    "category": "Oyuncak Kutuları",
    "supercategory": "Bebek Odası ve Tekstili"
  },
  {
    "model": "Mekta Home",
    "title": "Bebek ve Çocuk Odası Turncu Filli Balon Desenli Oyuncak Sepeti",
    "price": "418,95 TL",
    "rating": "N/A",
    "evaluation": "N/A",
    "category_url": "https://www.hepsiburada.com/oyuncak-kutulari-c-23020686?sayfa=35",
    "product_url": "https://www.hepsiburada.com/mekta-home-bebek-ve-cocuk-odasi-turncu-filli-balon-desenli-oyuncak-sepeti-pm-HBC00005K7NSZ",
    "category": "Oyuncak Kutuları",
    "supercategory": "Bebek Odası ve Tekstili"
  },
  {
    "model": "Mekta Home",
    "title": "Bebek ve Çocuk Odası Bulut Üzerinde Uyuyan Sevimli Ayı Desenli Gri Oyuncak Sepeti",
    "price": "418,95 TL",
    "rating": "N/A",
    "evaluation": "N/A",
    "category_url": "https://www.hepsiburada.com/oyuncak-kutulari-c-23020686?sayfa=35",
    "product_url": "https://www.hepsiburada.com/mekta-home-bebek-ve-cocuk-odasi-bulut-uzerinde-uyuyan-sevimli-ayi-desenli-gri-oyuncak-sepeti-pm-HBC00005K7N7T",
    "category": "Oyuncak Kutuları",
    "supercategory": "Bebek Odası ve Tekstili"
  },
  {
    "model": "Mekta Home",
    "title": "Bebek ve Çocuk Odası Küçük Denizci Kaptan Desenli Oyuncak Sepeti",
    "price": "418,95 TL",
    "rating": "N/A",
    "evaluation": "N/A",
    "category_url": "https://www.hepsiburada.com/oyuncak-kutulari-c-23020686?sayfa=35",
    "product_url": "https://www.hepsiburada.com/mekta-home-bebek-ve-cocuk-odasi-kucuk-denizci-kaptan-desenli-oyuncak-sepeti-pm-HBC00005K7NQL",
    "category": "Oyuncak Kutuları",
    "supercategory": "Bebek Odası ve Tekstili"
  },
  {
    "model": "Mekta Home",
    "title": "Bebek ve Çocuk Odası Soft Gökkuşağı ve Yol Desenli Oyuncak Sepeti",
    "price": "418,95 TL",
    "rating": "N/A",
    "evaluation": "N/A",
    "category_url": "https://www.hepsiburada.com/oyuncak-kutulari-c-23020686?sayfa=35",
    "product_url": "https://www.hepsiburada.com/mekta-home-bebek-ve-cocuk-odasi-soft-gokkusagi-ve-yol-desenli-oyuncak-sepeti-pm-HBC00005K7NC9",
    "category": "Oyuncak Kutuları",
    "supercategory": "Bebek Odası ve Tekstili"
  },
  {
    "model": "Mekta Home",
    "title": "Bebek ve Çocuk Odası Çelenk ve Yıldız Desenli Pembe Gri Çerçeveli Oyuncak Sepeti",
    "price": "418,95 TL",
    "rating": "N/A",
    "evaluation": "N/A",
    "category_url": "https://www.hepsiburada.com/oyuncak-kutulari-c-23020686?sayfa=35",
    "product_url": "https://www.hepsiburada.com/mekta-home-bebek-ve-cocuk-odasi-celenk-ve-yildiz-desenli-pembe-gri-cerceveli-oyuncak-sepeti-pm-HBC00005K7N81",
    "category": "Oyuncak Kutuları",
    "supercategory": "Bebek Odası ve Tekstili"
  },
  {
    "model": "Mekta Home",
    "title": "Bebek ve Çocuk Odası Yıldızlı Unicorn Desenli Oyuncak Sepeti",
    "price": "418,95 TL",
    "rating": "N/A",
    "evaluation": "N/A",
    "category_url": "https://www.hepsiburada.com/oyuncak-kutulari-c-23020686?sayfa=35",
    "product_url": "https://www.hepsiburada.com/mekta-home-bebek-ve-cocuk-odasi-yildizli-unicorn-desenli-oyuncak-sepeti-pm-HBC00005K7NZV",
    "category": "Oyuncak Kutuları",
    "supercategory": "Bebek Odası ve Tekstili"
  },
  {
    "model": "Mekta Home",
    "title": "Bebek ve Çocuk Odası Little Princess Desenli Oyuncak Sepeti",
    "price": "418,95 TL",
    "rating": "N/A",
    "evaluation": "N/A",
    "category_url": "https://www.hepsiburada.com/oyuncak-kutulari-c-23020686?sayfa=35",
    "product_url": "https://www.hepsiburada.com/mekta-home-bebek-ve-cocuk-odasi-little-princess-desenli-oyuncak-sepeti-pm-HBC00005K7NT7",
    "category": "Oyuncak Kutuları",
    "supercategory": "Bebek Odası ve Tekstili"
  },
  {
    "model": "instababyrooms",
    "title": "Dijital Baskılı Çok Amaçlı Sepet Model 01365",
    "price": "399 TL",
    "rating": "N/A",
    "evaluation": "N/A",
    "category_url": "https://www.hepsiburada.com/oyuncak-kutulari-c-23020686?sayfa=35",
    "product_url": "https://www.hepsiburada.com/instababyrooms-dijital-baskili-cok-amacli-sepet-model-01365-pm-HBC000044ZZ3E",
    "category": "Oyuncak Kutuları",
    "supercategory": "Bebek Odası ve Tekstili"
  },
  {
    "model": "Mekta Home",
    "title": "Bebek ve Çocuk Odası Mickey Mause Desenli Oyuncak Sepeti",
    "price": "418,95 TL",
    "rating": "N/A",
    "evaluation": "N/A",
    "category_url": "https://www.hepsiburada.com/oyuncak-kutulari-c-23020686?sayfa=35",
    "product_url": "https://www.hepsiburada.com/mekta-home-bebek-ve-cocuk-odasi-mickey-mause-desenli-oyuncak-sepeti-pm-HBC00005K7NV3",
    "category": "Oyuncak Kutuları",
    "supercategory": "Bebek Odası ve Tekstili"
  },
  {
    "model": "Mekta Home",
    "title": "Bebek ve Çocuk Odası Renkli Unicorn Desenli Beyaz Oyuncak Sepeti",
    "price": "418,95 TL",
    "rating": "N/A",
    "evaluation": "N/A",
    "category_url": "https://www.hepsiburada.com/oyuncak-kutulari-c-23020686?sayfa=35",
    "product_url": "https://www.hepsiburada.com/mekta-home-bebek-ve-cocuk-odasi-renkli-unicorn-desenli-beyaz-oyuncak-sepeti-pm-HBC00005K7NQ9",
    "category": "Oyuncak Kutuları",
    "supercategory": "Bebek Odası ve Tekstili"
  },
  {
    "model": "instababyrooms",
    "title": "Dijital Baskılı Çok Amaçlı Sepet Model 40017",
    "price": "399 TL",
    "rating": "N/A",
    "evaluation": "N/A",
    "category_url": "https://www.hepsiburada.com/oyuncak-kutulari-c-23020686?sayfa=35",
    "product_url": "https://www.hepsiburada.com/instababyrooms-dijital-baskili-cok-amacli-sepet-model-40017-pm-HBC000044ZZMM",
    "category": "Oyuncak Kutuları",
    "supercategory": "Bebek Odası ve Tekstili"
  },
  {
    "model": "Dmxtop",
    "title": "Çocuk Oyuncak Saklama Çantası - Beyaz (Yurt Dışından)",
    "price": "1.063,20 TL",
    "rating": "5",
    "evaluation": "(2)",
    "category_url": "https://www.hepsiburada.com/oyuncak-kutulari-c-23020686?sayfa=35",
    "product_url": "https://www.hepsiburada.com/dmxtop-cocuk-oyuncak-saklama-cantasi-beyaz-yurt-disindan-pm-HBC00003WNEIE",
    "category": "Oyuncak Kutuları",
    "supercategory": "Bebek Odası ve Tekstili"
  },
  {
    "model": "Love Home",
    "title": "Hayvan Figürlü Oyuncak Saklama Kutusu (Yurt Dışından)",
    "price": "1.346,80 TL",
    "rating": "N/A",
    "evaluation": "N/A",
    "category_url": "https://www.hepsiburada.com/oyuncak-kutulari-c-23020686?sayfa=35",
    "product_url": "https://www.hepsiburada.com/love-home-hayvan-figurlu-oyuncak-saklama-kutusu-yurt-disindan-pm-HBC00002K3IQQ",
    "category": "Oyuncak Kutuları",
    "supercategory": "Bebek Odası ve Tekstili"
  },
  {
    "model": "Featured Products",
    "title": "Yükseltilmiş Peluş Bebek Şeffaf Oyuncak Depolama Tüpü (Yurt Dışından)",
    "price": "1.444 TL",
    "rating": "N/A",
    "evaluation": "N/A",
    "category_url": "https://www.hepsiburada.com/oyuncak-kutulari-c-23020686?sayfa=35",
    "product_url": "https://www.hepsiburada.com/featured-products-yukseltilmis-pelus-bebek-seffaf-oyuncak-depolama-tupu-yurt-disindan-p-HBCV00007N7M0I",
    "category": "Oyuncak Kutuları",
    "supercategory": "Bebek Odası ve Tekstili"
  }
]