[
  {
    "model": "Dagi",
    "title": "Ekru File Uzun Kol Üst",
    "price": "1.149,98 TL",
    "rating": "N/A",
    "evaluation": "N/A",
    "category_url": "https://www.hepsiburada.com/pareo-c-60005256?sayfa=25",
    "product_url": "https://www.hepsiburada.com/ekru-file-uzun-kol-ust-p-HBCV000094HJOI",
    "category": "Pareo",
    "supercategory": "Plaj Giyim"
  },
  {
    "model": "Modamtn",
    "title": "Kadın Kolsuz Derin Oval V Detaylı Iki Yanı Büzgülü Triko Pareo",
    "price": "653,23 TL",
    "rating": "N/A",
    "evaluation": "N/A",
    "category_url": "https://www.hepsiburada.com/pareo-c-60005256?sayfa=25",
    "product_url": "https://www.hepsiburada.com/kadin-kolsuz-derin-oval-v-detayli-iki-yani-buzgulu-triko-pareo-pm-HBC000095VE5B",
    "category": "Pareo",
    "supercategory": "Plaj Giyim"
  },
  {
    "model": "İmoda",
    "title": "Kadın Siyah Tül Beli Lastikli Etek Görünümlü Pareo",
    "price": "136,49 TL",
    "rating": "N/A",
    "evaluation": "N/A",
    "category_url": "https://www.hepsiburada.com/pareo-c-60005256?sayfa=25",
    "product_url": "https://www.hepsiburada.com/kadin-siyah-tul-beli-lastikli-etek-gorunumlu-pareo-pm-HBC00009EBUPB",
    "category": "Pareo",
    "supercategory": "Plaj Giyim"
  },
  {
    "model": "Mareandpanda",
    "title": "Kadın File Desen Tam Boy Askılı Triko Pareo",
    "price": "728,81 TL",
    "rating": "N/A",
    "evaluation": "N/A",
    "category_url": "https://www.hepsiburada.com/pareo-c-60005256?sayfa=25",
    "product_url": "https://www.hepsiburada.com/kadin-file-desen-tam-boy-askili-triko-pareo-pm-HBC000095RP4A",
    "category": "Pareo",
    "supercategory": "Plaj Giyim"
  },
  {
    "model": "PayBuy",
    "title": "Bağlamalı Pareo Esnek Kumaş Ergonomik Kesim Su Sporları Için Şık Detaylı Yüksek Konfor",
    "price": "1.421,96 TL",
    "rating": "N/A",
    "evaluation": "N/A",
    "category_url": "https://www.hepsiburada.com/pareo-c-60005256?sayfa=25",
    "product_url": "https://www.hepsiburada.com/baglamali-pareo-esnek-kumas-ergonomik-kesim-su-sporlari-icin-sik-detayli-yuksek-konfor-p-HBCV00009DJ4A1",
    "category": "Pareo",
    "supercategory": "Plaj Giyim"
  },
  {
    "model": "Alfa Aksesuar 03",
    "title": "Kadın Siyah Beyaz Transparan Belden Bağlamalı Pareo 2'li",
    "price": "268,68 TL",
    "rating": "N/A",
    "evaluation": "N/A",
    "category_url": "https://www.hepsiburada.com/pareo-c-60005256?sayfa=25",
    "product_url": "https://www.hepsiburada.com/kadin-siyah-beyaz-transparan-belden-baglamali-pareo-2-li-pm-HBC000092GK4W",
    "category": "Pareo",
    "supercategory": "Plaj Giyim"
  },
  {
    "model": "Bernami",
    "title": "Özel Yanları Fırfırlı Mayo Üstüne Pareo Model 66000 Fırsat!!!",
    "price": "873 TL",
    "rating": "N/A",
    "evaluation": "N/A",
    "category_url": "https://www.hepsiburada.com/pareo-c-60005256?sayfa=25",
    "product_url": "https://www.hepsiburada.com/ozel-yanlari-firfirli-mayo-ustune-pareo-model-66000-firsat-pm-HBC00009C2WGJ",
    "category": "Pareo",
    "supercategory": "Plaj Giyim"
  },
  {
    "model": "Melenza",
    "title": "Kadın File Desen Tam Boy Askılı Triko Pareo",
    "price": "630,36 TL",
    "rating": "N/A",
    "evaluation": "N/A",
    "category_url": "https://www.hepsiburada.com/pareo-c-60005256?sayfa=25",
    "product_url": "https://www.hepsiburada.com/melenza-kadin-file-desen-tam-boy-askili-triko-pareo-p-HBCV000091W0I7",
    "category": "Pareo",
    "supercategory": "Plaj Giyim"
  },
  {
    "model": "GiyimCity",
    "title": "Kolları Püsküllü Şifon Kumaş Oversize Plaj Elbisesi",
    "price": "873,99 TL",
    "rating": "N/A",
    "evaluation": "N/A",
    "category_url": "https://www.hepsiburada.com/pareo-c-60005256?sayfa=25",
    "product_url": "https://www.hepsiburada.com/kollari-puskullu-sifon-kumas-oversize-plaj-elbisesi-p-HBCV000099A623",
    "category": "Pareo",
    "supercategory": "Plaj Giyim"
  },
  {
    "model": "Modamtn",
    "title": "Çift Yırtmaçlı Desenli Pareo",
    "price": "353,76 TL",
    "rating": "N/A",
    "evaluation": "N/A",
    "category_url": "https://www.hepsiburada.com/pareo-c-60005256?sayfa=25",
    "product_url": "https://www.hepsiburada.com/cift-yirtmacli-desenli-pareo-p-HBCV000095UBNH",
    "category": "Pareo",
    "supercategory": "Plaj Giyim"
  },
  {
    "model": "Kerem Yapı Market",
    "title": "Çicek Desenli Uzun Güpür Kimono",
    "price": "1.156,90 TL",
    "rating": "N/A",
    "evaluation": "N/A",
    "category_url": "https://www.hepsiburada.com/pareo-c-60005256?sayfa=25",
    "product_url": "https://www.hepsiburada.com/cicek-desenli-uzun-gupur-kimono-pm-HBC000093Z33M",
    "category": "Pareo",
    "supercategory": "Plaj Giyim"
  },
  {
    "model": "Bernami",
    "title": "Özel Özel Tasarım Bikini &amp; Mayo Üstüne Kırmızı Tül Pareo Fırsat!!!",
    "price": "305 TL",
    "rating": "N/A",
    "evaluation": "N/A",
    "category_url": "https://www.hepsiburada.com/pareo-c-60005256?sayfa=25",
    "product_url": "https://www.hepsiburada.com/ozel-ozel-tasarim-bikini-amp-mayo-ustune-kirmizi-tul-pareo-firsat-pm-HBC00009BZB4M",
    "category": "Pareo",
    "supercategory": "Plaj Giyim"
  },
  {
    "model": "N/A",
    "title": "Kadın Ispanyol Kollu Triko Tam Boy Pareo",
    "price": "468,57 TL",
    "rating": "N/A",
    "evaluation": "N/A",
    "category_url": "https://www.hepsiburada.com/pareo-c-60005256?sayfa=25",
    "product_url": "https://www.hepsiburada.com/kadin-ispanyol-kollu-triko-tam-boy-pareo-pm-HBC0000922MKJ",
    "category": "Pareo",
    "supercategory": "Plaj Giyim"
  },
  {
    "model": "Hayalet",
    "title": "Plaj Için Tasarım Leopar Desenli Kuşaklı Pareo Pantolon ve Tulum",
    "price": "525 TL",
    "rating": "N/A",
    "evaluation": "N/A",
    "category_url": "https://www.hepsiburada.com/pareo-c-60005256?sayfa=25",
    "product_url": "https://www.hepsiburada.com/plaj-icin-tasarim-leopar-desenli-kusakli-pareo-pantolon-ve-tulum-p-HBCV000096X5AE",
    "category": "Pareo",
    "supercategory": "Plaj Giyim"
  },
  {
    "model": "Adasea",
    "title": "Zeta Tesettür Pareo 1714",
    "price": "4.199 TL",
    "rating": "N/A",
    "evaluation": "N/A",
    "category_url": "https://www.hepsiburada.com/pareo-c-60005256?sayfa=25",
    "product_url": "https://www.hepsiburada.com/zeta-tesettur-pareo-1714-pm-HBC00007V3DYX",
    "category": "Pareo",
    "supercategory": "Plaj Giyim"
  },
  {
    "model": "Mareandpanda",
    "title": "Kadın File Desen Tam Boy Askılı Triko Pareo",
    "price": "728,81 TL",
    "rating": "N/A",
    "evaluation": "N/A",
    "category_url": "https://www.hepsiburada.com/pareo-c-60005256?sayfa=25",
    "product_url": "https://www.hepsiburada.com/kadin-file-desen-tam-boy-askili-triko-pareo-pm-HBC000095RR1L",
    "category": "Pareo",
    "supercategory": "Plaj Giyim"
  },
  {
    "model": "N/A",
    "title": "Kadın Triko Pareo",
    "price": "613,90 TL",
    "rating": "N/A",
    "evaluation": "N/A",
    "category_url": "https://www.hepsiburada.com/pareo-c-60005256?sayfa=25",
    "product_url": "https://www.hepsiburada.com/kadin-triko-pareo-pm-HBC00009BEILZ",
    "category": "Pareo",
    "supercategory": "Plaj Giyim"
  },
  {
    "model": "Louren",
    "title": "P15048 U Yaka Sırt Dekolteli Elbise",
    "price": "2.799 TL",
    "rating": "N/A",
    "evaluation": "N/A",
    "category_url": "https://www.hepsiburada.com/pareo-c-60005256?sayfa=25",
    "product_url": "https://www.hepsiburada.com/p15048-u-yaka-sirt-dekolteli-elbise-p-HBCV000095I0GX",
    "category": "Pareo",
    "supercategory": "Plaj Giyim"
  },
  {
    "model": "Louren",
    "title": "P15089 U/k Şifon Gömlek Pareo",
    "price": "3.299 TL",
    "rating": "N/A",
    "evaluation": "N/A",
    "category_url": "https://www.hepsiburada.com/pareo-c-60005256?sayfa=25",
    "product_url": "https://www.hepsiburada.com/p15089-u-k-sifon-gomlek-pareo-p-HBCV000095GXMY",
    "category": "Pareo",
    "supercategory": "Plaj Giyim"
  },
  {
    "model": "Lisalina",
    "title": "Mint Kadın Pareo LCBC0019",
    "price": "4.250 TL",
    "rating": "N/A",
    "evaluation": "N/A",
    "category_url": "https://www.hepsiburada.com/pareo-c-60005256?sayfa=25",
    "product_url": "https://www.hepsiburada.com/lisalina-mint-kadin-pareo-lcbc0019-pm-HBC000099JEEG",
    "category": "Pareo",
    "supercategory": "Plaj Giyim"
  },
  {
    "model": "Velmora Fashion",
    "title": "Kadın Ispanyol Kollu Triko Tam Boy Pareo",
    "price": "579,99 TL",
    "rating": "N/A",
    "evaluation": "N/A",
    "category_url": "https://www.hepsiburada.com/pareo-c-60005256?sayfa=25",
    "product_url": "https://www.hepsiburada.com/kadin-ispanyol-kollu-triko-tam-boy-pareo-pm-HBC0000925NNE",
    "category": "Pareo",
    "supercategory": "Plaj Giyim"
  },
  {
    "model": "Kerem Yapı Market",
    "title": "Müslin Kumaş Kimono-Antrasit",
    "price": "1.035,90 TL",
    "rating": "N/A",
    "evaluation": "N/A",
    "category_url": "https://www.hepsiburada.com/pareo-c-60005256?sayfa=25",
    "product_url": "https://www.hepsiburada.com/muslin-kumas-kimono-antrasit-p-HBCV000093Z201",
    "category": "Pareo",
    "supercategory": "Plaj Giyim"
  },
  {
    "model": "Modamtn",
    "title": "Kadın Eteği Büzgü Detay Boyundan Bağlamalı Mini Triko Pareo",
    "price": "526,18 TL",
    "rating": "N/A",
    "evaluation": "N/A",
    "category_url": "https://www.hepsiburada.com/pareo-c-60005256?sayfa=25",
    "product_url": "https://www.hepsiburada.com/kadin-etegi-buzgu-detay-boyundan-baglamali-mini-triko-pareo-pm-HBC0000998R7K",
    "category": "Pareo",
    "supercategory": "Plaj Giyim"
  },
  {
    "model": "Bernami",
    "title": "Özel File Kısa Kolsuz Mayo Üstüne Yazlık Kıyafet Model 608 Fırsat!!!",
    "price": "571 TL",
    "rating": "N/A",
    "evaluation": "N/A",
    "category_url": "https://www.hepsiburada.com/pareo-c-60005256?sayfa=25",
    "product_url": "https://www.hepsiburada.com/ozel-file-kisa-kolsuz-mayo-ustune-yazlik-kiyafet-model-608-firsat-pm-HBC00009C17GW",
    "category": "Pareo",
    "supercategory": "Plaj Giyim"
  },
  {
    "model": "Bernami",
    "title": "Özel File Kollu Kırmızı Pareo Mayo Üstüne Giyilebilirmodel 109 Fırsat!!!",
    "price": "571 TL",
    "rating": "N/A",
    "evaluation": "N/A",
    "category_url": "https://www.hepsiburada.com/pareo-c-60005256?sayfa=25",
    "product_url": "https://www.hepsiburada.com/ozel-file-kollu-kirmizi-pareo-mayo-ustune-giyilebilirmodel-109-firsat-pm-HBC00009C1RLL",
    "category": "Pareo",
    "supercategory": "Plaj Giyim"
  },
  {
    "model": "Dilmex",
    "title": "Kadın Kolsuz Derin Oval V Detaylı Iki Yanı Büzgülü Triko Pareo",
    "price": "1.067,29 TL",
    "rating": "N/A",
    "evaluation": "N/A",
    "category_url": "https://www.hepsiburada.com/pareo-c-60005256?sayfa=25",
    "product_url": "https://www.hepsiburada.com/kadin-kolsuz-derin-oval-v-detayli-iki-yani-buzgulu-triko-pareo-pm-HBC00009F4O4M",
    "category": "Pareo",
    "supercategory": "Plaj Giyim"
  },
  {
    "model": "LYYN",
    "title": "Şal Desenli Önü Açık Kısa Pareo",
    "price": "2.466,81 TL",
    "rating": "N/A",
    "evaluation": "N/A",
    "category_url": "https://www.hepsiburada.com/pareo-c-60005256?sayfa=25",
    "product_url": "https://www.hepsiburada.com/sal-desenli-onu-acik-kisa-pareo-pm-HBC00008U3BO0",
    "category": "Pareo",
    "supercategory": "Plaj Giyim"
  },
  {
    "model": "N/A",
    "title": "Kadın Siyah Transparan Belden Bağlamalı Pareo",
    "price": "375,95 TL",
    "rating": "N/A",
    "evaluation": "N/A",
    "category_url": "https://www.hepsiburada.com/pareo-c-60005256?sayfa=25",
    "product_url": "https://www.hepsiburada.com/kadin-siyah-transparan-belden-baglamali-pareo-pm-HBC000099JWSP",
    "category": "Pareo",
    "supercategory": "Plaj Giyim"
  },
  {
    "model": "Ruko Mayo",
    "title": "Rukomayo Pembe Çiçek Desenli Uzunkol Esnek Şifon Kumaş Elbise Pareo",
    "price": "1.249 TL",
    "rating": "N/A",
    "evaluation": "N/A",
    "category_url": "https://www.hepsiburada.com/pareo-c-60005256?sayfa=25",
    "product_url": "https://www.hepsiburada.com/rukomayo-pembe-cicek-desenli-uzunkol-esnek-sifon-kumas-elbise-pareo-pm-HBC00008TJDHK",
    "category": "Pareo",
    "supercategory": "Plaj Giyim"
  },
  {
    "model": "N/A",
    "title": "Kadın File ve Sendy Kumaş Broş Detaylı Transparan Pareo",
    "price": "1.504,90 TL",
    "rating": "N/A",
    "evaluation": "N/A",
    "category_url": "https://www.hepsiburada.com/pareo-c-60005256?sayfa=25",
    "product_url": "https://www.hepsiburada.com/kadin-file-ve-sendy-kumas-bros-detayli-transparan-pareo-pm-HBC00009BG68M",
    "category": "Pareo",
    "supercategory": "Plaj Giyim"
  },
  {
    "model": "MiraLive",
    "title": "Marsilyan- Kadın Siyah Transparan Belden Bağlamalı Pareo",
    "price": "334,19 TL",
    "rating": "N/A",
    "evaluation": "N/A",
    "category_url": "https://www.hepsiburada.com/pareo-c-60005256?sayfa=25",
    "product_url": "https://www.hepsiburada.com/marsilyan-kadin-siyah-transparan-belden-baglamali-pareo-pm-HBC00009CU6UH",
    "category": "Pareo",
    "supercategory": "Plaj Giyim"
  },
  {
    "model": "Bernami",
    "title": "Özel Kadın Askılı Derin Sırt Dekolteli Ajurlu Triko Pareo Fırsat!!!",
    "price": "1.173 TL",
    "rating": "N/A",
    "evaluation": "N/A",
    "category_url": "https://www.hepsiburada.com/pareo-c-60005256?sayfa=25",
    "product_url": "https://www.hepsiburada.com/ozel-kadin-askili-derin-sirt-dekolteli-ajurlu-triko-pareo-firsat-pm-HBC00009BXVVN",
    "category": "Pareo",
    "supercategory": "Plaj Giyim"
  },
  {
    "model": "Dagi",
    "title": "Multicolor Etek",
    "price": "1.499,98 TL",
    "rating": "N/A",
    "evaluation": "N/A",
    "category_url": "https://www.hepsiburada.com/pareo-c-60005256?sayfa=25",
    "product_url": "https://www.hepsiburada.com/multicolor-etek-p-HBCV000094JOYD",
    "category": "Pareo",
    "supercategory": "Plaj Giyim"
  },
  {
    "model": "Dagi",
    "title": "Vizon Önden Bağlamalı Etek",
    "price": "1.499,98 TL",
    "rating": "N/A",
    "evaluation": "N/A",
    "category_url": "https://www.hepsiburada.com/pareo-c-60005256?sayfa=25",
    "product_url": "https://www.hepsiburada.com/vizon-onden-baglamali-etek-p-HBCV000094JOW6",
    "category": "Pareo",
    "supercategory": "Plaj Giyim"
  },
  {
    "model": "PayBuy",
    "title": "Bağlamalı Pareo Esnek Kumaş Özel Tasarım Hızlı Kuruyan Plaj ve Havuz Için",
    "price": "1.276,65 TL",
    "rating": "N/A",
    "evaluation": "N/A",
    "category_url": "https://www.hepsiburada.com/pareo-c-60005256?sayfa=25",
    "product_url": "https://www.hepsiburada.com/baglamali-pareo-esnek-kumas-ozel-tasarim-hizli-kuruyan-plaj-ve-havuz-icin-p-HBCV00009DJ4HO",
    "category": "Pareo",
    "supercategory": "Plaj Giyim"
  }
]